sysgen/__init__.py
sysgen/cli.py
sysgen-0.2.2.dist-info/licenses/LICENSE
sysgen-0.2.2.dist-info/METADATA
sysgen-0.2.2.dist-info/WHEEL
sysgen-0.2.2.dist-info/entry_points.txt
sysgen-0.2.2.dist-info/top_level.txt
sysgen-0.2.2.dist-info/RECORD
