Metadata-Version: 2.4
Name: sysgen
Version: 0.2.2
Summary: SysGen - High-quality synthetic datasets creating tool using Gemini API
Home-page: https://github.com/adhishtanaka/sysgen
Author: Adhishtanaka
Author-email: kulasoooriyaa@gmail.com
License: MIT
Project-URL: Bug Reports, https://github.com/adhishtanaka/sysgen/issues
Project-URL: Source, https://github.com/adhishtanaka/sysgen
Project-URL: Documentation, https://github.com/adhishtanaka/sysgen#readme
Keywords: ai machine-learning dataset generation gemini synthetic-data qa-generation
Classifier: Development Status :: 4 - Beta
Classifier: Intended Audience :: Developers
Classifier: Intended Audience :: Science/Research
Classifier: License :: OSI Approved :: MIT License
Classifier: Programming Language :: Python :: 3
Classifier: Programming Language :: Python :: 3.8
Classifier: Programming Language :: Python :: 3.9
Classifier: Programming Language :: Python :: 3.10
Classifier: Programming Language :: Python :: 3.11
Classifier: Programming Language :: Python :: 3.12
Classifier: Topic :: Scientific/Engineering :: Artificial Intelligence
Classifier: Topic :: Software Development :: Libraries :: Python Modules
Classifier: Topic :: Text Processing :: Linguistic
Classifier: Operating System :: OS Independent
Requires-Python: >=3.8
License-File: LICENSE
Requires-Dist: google-genai
Requires-Dist: sentence-transformers
Requires-Dist: scikit-learn
Requires-Dist: tiktoken
Requires-Dist: torch
Requires-Dist: transformers
Requires-Dist: numpy
Requires-Dist: scipy
Requires-Dist: tf-keras
Dynamic: author
Dynamic: author-email
Dynamic: classifier
Dynamic: description
Dynamic: description-content-type
Dynamic: home-page
Dynamic: keywords
Dynamic: license
Dynamic: license-file
Dynamic: project-url
Dynamic: requires-dist
Dynamic: requires-python
Dynamic: summary
